{
  "openapi": "3.1.1",
  "info": {
    "title": "MOD10 | v1",
    "version": "1.0.0"
  },
  "servers": [
    {
      "url": "http://localhost:5239"
    }
  ],
  "paths": {
    "/api/Game": {
      "get": {
        "tags": [
          "Game"
        ],
        "responses": {
          "200": {
            "description": "OK",
            "content": {
              "text/plain": {
                "schema": {
                  "type": "array",
                  "items": {
                    "$ref": "#/components/schemas/Game"
                  }
                }
              },
              "application/json": {
                "schema": {
                  "type": "array",
                  "items": {
                    "$ref": "#/components/schemas/Game"
                  }
                }
              },
              "text/json": {
                "schema": {
                  "type": "array",
                  "items": {
                    "$ref": "#/components/schemas/Game"
                  }
                }
              }
            }
          }
        }
      },
      "post": {
        "tags": [
          "Game"
        ],
        "requestBody": {
          "content": {
            "application/json": {
              "schema": {
                "$ref": "#/components/schemas/Game"
              }
            },
            "text/json": {
              "schema": {
                "$ref": "#/components/schemas/Game"
              }
            },
            "application/*+json": {
              "schema": {
                "$ref": "#/components/schemas/Game"
              }
            }
          },
          "required": true
        },
        "responses": {
          "200": {
            "description": "OK"
          }
        }
      }
    },
    "/api/Game/{id}": {
      "get": {
        "tags": [
          "Game"
        ],
        "parameters": [
          {
            "name": "id",
            "in": "path",
            "required": true,
            "schema": {
              "pattern": "^-?(?:0|[1-9]\\d*)$",
              "type": [
                "integer",
                "string"
              ],
              "format": "int32"
            }
          }
        ],
        "responses": {
          "200": {
            "description": "OK",
            "content": {
              "text/plain": {
                "schema": {
                  "$ref": "#/components/schemas/Game"
                }
              },
              "application/json": {
                "schema": {
                  "$ref": "#/components/schemas/Game"
                }
              },
              "text/json": {
                "schema": {
                  "$ref": "#/components/schemas/Game"
                }
              }
            }
          }
        }
      },
      "put": {
        "tags": [
          "Game"
        ],
        "parameters": [
          {
            "name": "id",
            "in": "path",
            "required": true,
            "schema": {
              "pattern": "^-?(?:0|[1-9]\\d*)$",
              "type": [
                "integer",
                "string"
              ],
              "format": "int32"
            }
          }
        ],
        "requestBody": {
          "content": {
            "application/json": {
              "schema": {
                "$ref": "#/components/schemas/Game"
              }
            },
            "text/json": {
              "schema": {
                "$ref": "#/components/schemas/Game"
              }
            },
            "application/*+json": {
              "schema": {
                "$ref": "#/components/schemas/Game"
              }
            }
          },
          "required": true
        },
        "responses": {
          "200": {
            "description": "OK"
          }
        }
      },
      "delete": {
        "tags": [
          "Game"
        ],
        "parameters": [
          {
            "name": "id",
            "in": "path",
            "required": true,
            "schema": {
              "pattern": "^-?(?:0|[1-9]\\d*)$",
              "type": [
                "integer",
                "string"
              ],
              "format": "int32"
            }
          }
        ],
        "responses": {
          "200": {
            "description": "OK"
          }
        }
      }
    },
    "/WeatherForecast": {
      "get": {
        "tags": [
          "WeatherForecast"
        ],
        "operationId": "GetWeatherForecast",
        "responses": {
          "200": {
            "description": "OK",
            "content": {
              "text/plain": {
                "schema": {
                  "type": "array",
                  "items": {
                    "$ref": "#/components/schemas/WeatherForecast"
                  }
                }
              },
              "application/json": {
                "schema": {
                  "type": "array",
                  "items": {
                    "$ref": "#/components/schemas/WeatherForecast"
                  }
                }
              },
              "text/json": {
                "schema": {
                  "type": "array",
                  "items": {
                    "$ref": "#/components/schemas/WeatherForecast"
                  }
                }
              }
            }
          }
        }
      }
    }
  },
  "components": {
    "schemas": {
      "Game": {
        "required": [
          "id",
          "nama",
          "developer",
          "tahunRilis",
          "genre",
          "rating",
          "isOnline",
          "harga"
        ],
        "type": "object",
        "properties": {
          "id": {
            "pattern": "^-?(?:0|[1-9]\\d*)$",
            "type": [
              "integer",
              "string"
            ],
            "format": "int32"
          },
          "nama": {
            "type": "string"
          },
          "developer": {
            "type": "string"
          },
          "tahunRilis": {
            "pattern": "^-?(?:0|[1-9]\\d*)$",
            "type": [
              "integer",
              "string"
            ],
            "format": "int32"
          },
          "genre": {
            "type": "string"
          },
          "rating": {
            "pattern": "^-?(?:0|[1-9]\\d*)(?:\\.\\d+)?(?:[eE][+-]?\\d+)?$",
            "type": [
              "number",
              "string"
            ],
            "format": "double"
          },
          "isOnline": {
            "type": "boolean"
          },
          "harga": {
            "pattern": "^-?(?:0|[1-9]\\d*)$",
            "type": [
              "integer",
              "string"
            ],
            "format": "int32"
          }
        }
      },
      "WeatherForecast": {
        "type": "object",
        "properties": {
          "date": {
            "type": "string",
            "format": "date"
          },
          "temperatureC": {
            "pattern": "^-?(?:0|[1-9]\\d*)$",
            "type": [
              "integer",
              "string"
            ],
            "format": "int32"
          },
          "temperatureF": {
            "pattern": "^-?(?:0|[1-9]\\d*)$",
            "type": [
              "integer",
              "string"
            ],
            "format": "int32"
          },
          "summary": {
            "type": [
              "null",
              "string"
            ]
          }
        }
      }
    }
  },
  "tags": [
    {
      "name": "Game"
    },
    {
      "name": "WeatherForecast"
    }
  ]
}